python_socks/__init__.py
python_socks/_abc.py
python_socks/_errors.py
python_socks/_helpers.py
python_socks/_types.py
python_socks/_version.py
python_socks/py.typed
python_socks/_connectors/__init__.py
python_socks/_connectors/abc.py
python_socks/_connectors/factory_async.py
python_socks/_connectors/factory_sync.py
python_socks/_connectors/http_async.py
python_socks/_connectors/http_sync.py
python_socks/_connectors/socks4_async.py
python_socks/_connectors/socks4_sync.py
python_socks/_connectors/socks5_async.py
python_socks/_connectors/socks5_sync.py
python_socks/_protocols/__init__.py
python_socks/_protocols/errors.py
python_socks/_protocols/http.py
python_socks/_protocols/socks4.py
python_socks/_protocols/socks5.py
python_socks/async_/__init__.py
python_socks/async_/_proxy_chain.py
python_socks/async_/anyio/__init__.py
python_socks/async_/anyio/_chain.py
python_socks/async_/anyio/_connect.py
python_socks/async_/anyio/_proxy.py
python_socks/async_/anyio/_resolver.py
python_socks/async_/anyio/_stream.py
python_socks/async_/anyio/v2/__init__.py
python_socks/async_/anyio/v2/_chain.py
python_socks/async_/anyio/v2/_connect.py
python_socks/async_/anyio/v2/_proxy.py
python_socks/async_/anyio/v2/_stream.py
python_socks/async_/asyncio/__init__.py
python_socks/async_/asyncio/_connect.py
python_socks/async_/asyncio/_proxy.py
python_socks/async_/asyncio/_resolver.py
python_socks/async_/asyncio/_stream.py
python_socks/async_/asyncio/v2/__init__.py
python_socks/async_/asyncio/v2/_chain.py
python_socks/async_/asyncio/v2/_connect.py
python_socks/async_/asyncio/v2/_proxy.py
python_socks/async_/asyncio/v2/_stream.py
python_socks/async_/curio/__init__.py
python_socks/async_/curio/_connect.py
python_socks/async_/curio/_proxy.py
python_socks/async_/curio/_resolver.py
python_socks/async_/curio/_stream.py
python_socks/async_/trio/__init__.py
python_socks/async_/trio/_connect.py
python_socks/async_/trio/_proxy.py
python_socks/async_/trio/_resolver.py
python_socks/async_/trio/_stream.py
python_socks-2.6.0.dist-info/LICENSE.txt
python_socks-2.6.0.dist-info/METADATA
python_socks-2.6.0.dist-info/WHEEL
python_socks-2.6.0.dist-info/top_level.txt
python_socks-2.6.0.dist-info/RECORD
