Metadata-Version: 2.1
Name: python-socks
Version: 2.6.0
Summary: Proxy (SOCKS4, SOCKS5, HTTP CONNECT) client for Python
Author-email: Roman Snegirev <snegiryev@gmail.com>
License: Apache-2.0
Project-URL: homepage, https://github.com/romis2012/python-socks
Project-URL: repository, https://github.com/romis2012/python-socks
Keywords: socks,socks5,socks4,http,proxy,asyncio,trio,curio,anyio
Classifier: Development Status :: 5 - Production/Stable
Classifier: Programming Language :: Python
Classifier: Programming Language :: Python :: 3
Classifier: Programming Language :: Python :: 3 :: Only
Classifier: Programming Language :: Python :: 3.8
Classifier: Programming Language :: Python :: 3.9
Classifier: Programming Language :: Python :: 3.10
Classifier: Programming Language :: Python :: 3.11
Classifier: Programming Language :: Python :: 3.12
Classifier: Programming Language :: Python :: 3.13
Classifier: Operating System :: MacOS
Classifier: Operating System :: Microsoft
Classifier: Operating System :: POSIX :: Linux
Classifier: Topic :: Internet :: WWW/HTTP
Classifier: Intended Audience :: Developers
Classifier: Framework :: AsyncIO
Classifier: Framework :: Trio
Classifier: License :: OSI Approved :: Apache Software License
Requires-Python: >=3.8.0
License-File: LICENSE.txt
Provides-Extra: asyncio
Requires-Dist: async-timeout>=4.0; python_version < "3.11" and extra == "asyncio"
Provides-Extra: trio
Requires-Dist: trio>=0.24; extra == "trio"
Provides-Extra: curio
Requires-Dist: curio>=1.4; extra == "curio"
Provides-Extra: anyio
Requires-Dist: anyio<5.0.0,>=3.3.4; extra == "anyio"
